dropblame/__init__.py
dropblame-0.0.1.dist-info/METADATA
dropblame-0.0.1.dist-info/DESCRIPTION.rst
dropblame-0.0.1.dist-info/RECORD
dropblame-0.0.1.dist-info/entry_points.txt
dropblame-0.0.1.dist-info/WHEEL
dropblame-0.0.1.dist-info/top_level.txt
dropblame-0.0.1.dist-info/metadata.json
