Metadata-Version: 2.0
Name: dropblame
Version: 0.0.1
Summary: "git blame" for Dropbox files
Home-page: https://github.com/mispy/dropblame
Author: Jaiden Mispy
Author-email: jaiden@mispy.me
License: UNKNOWN
Keywords: git dropbox command-line
Platform: UNKNOWN
Classifier: License :: OSI Approved :: MIT License
Classifier: Programming Language :: Python :: 2.7
Classifier: Topic :: Utilities
Requires-Dist: dropbox
Requires-Dist: pyyaml
Requires-Dist: ndg-httpsclient
